p3ai_agent/__init__.py
p3ai_agent/agent.py
p3ai_agent/communication.py
p3ai_agent/identity.py
p3ai_agent/search.py
p3ai_agent/utils.py
p3ai_agent-0.1.5.dist-info/METADATA
p3ai_agent-0.1.5.dist-info/WHEEL
p3ai_agent-0.1.5.dist-info/RECORD
