Metadata-Version: 2.1
Name: p3ai-agent
Version: 0.1.5
Summary: A Langchain and Autogen wrapper that enables agents to communicate and establish identity on the P3 AI Network. This SDK provides three core capabilities: Identity Management, Agent Discovery & Search, and MQTT-based Communication.
Author: Swapnil Shinde
Author-email: swapnilshinde9382@gmail.com
Requires-Python: >=3.12,<4.0
Classifier: Programming Language :: Python :: 3
Classifier: Programming Language :: Python :: 3.12
Requires-Dist: base58 (>=2.1.1,<3.0.0)
Requires-Dist: cryptography (>=45.0.4,<46.0.0)
Requires-Dist: langchain (>=0.3.22,<0.4.0)
Requires-Dist: langchain-core (>=0.3.49,<0.4.0)
Requires-Dist: langchain-openai (>=0.3.11,<0.4.0)
Requires-Dist: paho-mqtt (>=2.1.0,<3.0.0)
